render_block/__init__.py
render_block/base.py
render_block/django.py
render_block/exceptions.py
render_block/jinja2.py
django_render_block-0.10.dist-info/LICENSE
django_render_block-0.10.dist-info/METADATA
django_render_block-0.10.dist-info/WHEEL
django_render_block-0.10.dist-info/top_level.txt
django_render_block-0.10.dist-info/RECORD
