Metadata-Version: 2.1
Name: django-render-block
Version: 0.10
Summary: Render a particular block from a template to a string.
Home-page: https://github.com/clokep/django-render-block
Author: Patrick Cloke
Author-email: clokep@patrick.cloke.us
License: ISC
Project-URL: Documentation, https://github.com/clokep/django-render-block/blob/main/README.rst
Project-URL: Release notes, https://github.com/clokep/django-render-block/blob/main/CHANGELOG.rst
Project-URL: Source, https://github.com/clokep/django-render-block
Project-URL: Tracker, https://github.com/clokep/django-render-block/issues
Keywords: [django,template,block,templates,render,context]
Classifier: Development Status :: 4 - Beta
Classifier: Intended Audience :: Developers
Classifier: Topic :: Software Development :: Libraries :: Python Modules
Classifier: Environment :: Web Environment
Classifier: Topic :: Internet
Classifier: Framework :: Django
Classifier: Framework :: Django :: 3.2
Classifier: Framework :: Django :: 4.1
Classifier: Programming Language :: Python
Classifier: Programming Language :: Python :: 3.8
Classifier: Programming Language :: Python :: 3.9
Classifier: Programming Language :: Python :: 3.10
Classifier: Programming Language :: Python :: 3.11
Classifier: Programming Language :: Python :: 3.12
Classifier: License :: OSI Approved :: ISC License (ISCL)
Requires-Python: >=3.8
License-File: LICENSE
Requires-Dist: django>=3.2
Provides-Extra: dev
Requires-Dist: Jinja2>=2.8; extra == "dev"
